py_horned_owl-1.2.1.dist-info/METADATA
py_horned_owl-1.2.1.dist-info/WHEEL
py_horned_owl-1.2.1.dist-info/licenses/COPYING
py_horned_owl-1.2.1.dist-info/licenses/COPYING.lesser
pyhornedowl.libs/libgcc_s-1e52349c.so.1
pyhornedowl/__init__.py
pyhornedowl/__init__.pyi
pyhornedowl/model/__init__.py
pyhornedowl/model/__init__.pyi
pyhornedowl/py.typed
pyhornedowl/pyhornedowl.abi3.so
py_horned_owl-1.2.1.dist-info/RECORD
