Metadata-Version: 2.4
Name: py-horned-owl
Version: 1.2.1
Classifier: Programming Language :: Rust
Classifier: Programming Language :: Python :: Implementation :: CPython
Classifier: Programming Language :: Python :: Implementation :: PyPy
License-File: COPYING
License-File: COPYING.lesser
Author: Janna Hastings <j.hastings@ucl.ac.uk>
Author-email: Janna Hastings <j.hastings@ucl.ac.uk>
License: LGPL-3.0-or-later
Requires-Python: >=3.7
